{
  "batch_id": 383,
  "mentors": [
    "李福荔",
    "杨中民",
    "薛若军",
    "赵晟",
    "靳标",
    "蔡忠亮",
    "nan",
    "孔谋夫",
    "鲁英灿",
    "陈德富",
    "徐静",
    "白丽",
    "nan",
    "李连崇",
    "喻泽红",
    "刘新",
    "赵立业",
    "nan",
    "张建宇",
    "秦勇"
  ],
  "response": {
    "mentors": [
      {
        "mentor_index": 1,
        "name": "李福荔",
        "导师能力": {
          "score": 9,
          "reason": "国际A/B类期刊十余篇，跨方向能力强"
        },
        "经费情况": {
          "score": 8,
          "reason": "已申请基金，经费充足"
        },
        "学生补助": {
          "score": 5,
          "reason": "未提及具体补助金额"
        },
        "师生关系": {
          "score": 10,
          "reason": "邻家姐姐式关怀，有问必答，尊重学生"
        },
        "工作时间": {
          "score": 5,
          "reason": "未提及工作时间安排"
        },
        "毕业去向": {
          "score": 6,
          "reason": "尚无毕业生，但重视人格与学术培养"
        },
        "overall_recommendation": "学术实力强、师生关系极佳，适合追求扎实科研与温暖导学关系的学生"
      },
      {
        "mentor_index": 2,
        "name": "杨中民",
        "导师能力": {
          "score": 8,
          "reason": "长江/杰青，学术地位高"
        },
        "经费情况": {
          "score": 9,
          "reason": "实验经费充裕，项目资源丰富"
        },
        "学生补助": {
          "score": 4,
          "reason": "统一500元，属偏低水平"
        },
        "师生关系": {
          "score": 3,
          "reason": "基本见不到人，管理松散缺乏互动"
        },
        "工作时间": {
          "score": 7,
          "reason": "朝九晚五双休，时间安排合理"
        },
        "毕业去向": {
          "score": 4,
          "reason": "完全不干预就业，支持度低"
        },
        "overall_recommendation": "学术平台好但指导缺位，适合高度自律、目标明确且不依赖导师推力的学生"
      },
      {
        "mentor_index": 3,
        "name": "薛若军",
        "导师能力": {
          "score": 2,
          "reason": "刚博士毕业，学术积累薄弱"
        },
        "经费情况": {
          "score": 1,
          "reason": "基本无经费，依赖自学"
        },
        "学生补助": {
          "score": 5,
          "reason": "未提及补助情况"
        },
        "师生关系": {
          "score": 1,
          "reason": "让学生干杂活、不尊重学生时间"
        },
        "工作时间": {
          "score": 2,
          "reason": "杂务繁重，边界模糊，隐性超负荷"
        },
        "毕业去向": {
          "score": 3,
          "reason": "完全不提供就业支持，靠学生自谋"
        },
        "overall_recommendation": "存在严重剥削倾向，强烈不推荐，尤其对需结构化指导的新生"
      },
      {
        "mentor_index": 4,
        "name": "赵晟",
        "导师能力": {
          "score": 9,
          "reason": "斯坦福背景，思路新颖，指导本科生能力强"
        },
        "经费情况": {
          "score": 5,
          "reason": "未明确提及经费情况"
        },
        "学生补助": {
          "score": 5,
          "reason": "未提及补助金额"
        },
        "师生关系": {
          "score": 10,
          "reason": "亲和温暖，生日送蛋糕，一视同仁"
        },
        "工作时间": {
          "score": 5,
          "reason": "未说明具体作息要求"
        },
        "毕业去向": {
          "score": 5,
          "reason": "未提及职业发展支持"
        },
        "overall_recommendation": "青年海归良师，重育人温度与能力启蒙，适合本科直博或重基础训练者"
      },
      {
        "mentor_index": 5,
        "name": "靳标",
        "导师能力": {
          "score": 1,
          "reason": "答辩时不懂专业内容，欺软怕硬"
        },
        "经费情况": {
          "score": 5,
          "reason": "未提及经费情况"
        },
        "学生补助": {
          "score": 5,
          "reason": "未提及补助情况"
        },
        "师生关系": {
          "score": 2,
          "reason": "私下解释不清，缺乏基本学术尊重"
        },
        "工作时间": {
          "score": 5,
          "reason": "未提及工作时间安排"
        },
        "毕业去向": {
          "score": 2,
          "reason": "无任何就业支持迹象"
        },
        "overall_recommendation": "学术与师德双重风险，应绝对规避，尤其避免毕设/入学阶段接触"
      },
      {
        "mentor_index": 6,
        "name": "蔡忠亮",
        "导师能力": {
          "score": 6,
          "reason": "方向性指导为主，科研偏弱但工程强"
        },
        "经费情况": {
          "score": 9,
          "reason": "工程项目极多，平台资源丰富"
        },
        "学生补助": {
          "score": 10,
          "reason": "资环院最高工资，慷慨明确"
        },
        "师生关系": {
          "score": 9,
          "reason": "耐心、关心未来，团队有爱"
        },
        "工作时间": {
          "score": 7,
          "reason": "允许少量实习，节奏较弹性"
        },
        "毕业去向": {
          "score": 8,
          "reason": "硕士抢着要，事业单位匹配度高"
        },
        "overall_recommendation": "工程实践导向首选，薪资高、氛围好、就业稳，适合非教职路径学生"
      },
      {
        "mentor_index": 7,
        "name": "nan",
        "导师能力": {
          "score": 9,
          "reason": "机器人领域大牛，学术影响力强"
        },
        "经费情况": {
          "score": 10,
          "reason": "想法合理即支持，经费极其充足"
        },
        "学生补助": {
          "score": 8,
          "reason": "天大机械前列，强调学生经济独立"
        },
        "师生关系": {
          "score": 8,
          "reason": "一视同仁，批评指正+关心去向"
        },
        "工作时间": {
          "score": 8,
          "reason": "无硬性要求，重结果导向"
        },
        "毕业去向": {
          "score": 8,
          "reason": "百强企业与创业均有成功案例"
        },
        "overall_recommendation": "顶尖平台+人性化管理，科研与工业界双轨发展理想选择"
      },
      {
        "mentor_index": 8,
        "name": "孔谋夫",
        "导师能力": {
          "score": 6,
          "reason": "教学效果显著（模电成绩跃升）"
        },
        "经费情况": {
          "score": 5,
          "reason": "未提及经费情况"
        },
        "学生补助": {
          "score": 5,
          "reason": "评价者为本科生，非其研究生"
        },
        "师生关系": {
          "score": 5,
          "reason": "仅知尊师，无直接师生互动描述"
        },
        "工作时间": {
          "score": 5,
          "reason": "未提及工作时间安排"
        },
        "毕业去向": {
          "score": 5,
          "reason": "未涉及毕业支持信息"
        },
        "overall_recommendation": "信息严重不足，无法评估研究生指导适配性，建议进一步核实"
      },
      {
        "mentor_index": 9,
        "name": "鲁英灿",
        "导师能力": {
          "score": 5,
          "reason": "曾有名气，但已离校，现状不明"
        },
        "经费情况": {
          "score": 5,
          "reason": "未提及经费情况"
        },
        "学生补助": {
          "score": 5,
          "reason": "未提及补助情况"
        },
        "师生关系": {
          "score": 2,
          "reason": "已不在校任职，无法建立有效指导关系"
        },
        "工作时间": {
          "score": 5,
          "reason": "未提及工作时间安排"
        },
        "毕业去向": {
          "score": 1,
          "reason": "无法提供任何毕业支持"
        },
        "overall_recommendation": "已离职且健康状态存疑，不具备招生与指导可行性，应排除"
      },
      {
        "mentor_index": 10,
        "name": "陈德富",
        "导师能力": {
          "score": 7,
          "reason": "认真细致，但实验经费投入受质疑"
        },
        "经费情况": {
          "score": 4,
          "reason": "被其他导师质疑不舍得花钱做实验"
        },
        "学生补助": {
          "score": 5,
          "reason": "未提及具体补助金额"
        },
        "师生关系": {
          "score": 8,
          "reason": "评价为‘好老师’，细致认真"
        },
        "工作时间": {
          "score": 5,
          "reason": "未提及工作时间安排"
        },
        "毕业去向": {
          "score": 5,
          "reason": "未提及职业发展支持"
        },
        "overall_recommendation": "治学严谨但资源投入谨慎，适合重学术训练、对实验成本敏感的学生"
      },
      {
        "mentor_index": 11,
        "name": "徐静",
        "导师能力": {
          "score": 9,
          "reason": "结构光方向大牛，学术影响力突出"
        },
        "经费情况": {
          "score": 5,
          "reason": "未提及经费情况"
        },
        "学生补助": {
          "score": 5,
          "reason": "未提及补助金额"
        },
        "师生关系": {
          "score": 9,
          "reason": "亦师亦友，实验室气氛良好"
        },
        "工作时间": {
          "score": 7,
          "reason": "允许实习，管理弹性"
        },
        "毕业去向": {
          "score": 7,
          "reason": "支持实习，隐含就业导向"
        },
        "overall_recommendation": "清华顶尖方向+良性导学关系，适合追求学术深度与职业灵活性的优秀生源"
      },
      {
        "mentor_index": 12,
        "name": "白丽",
        "导师能力": {
          "score": 9,
          "reason": "食品安全领域科研能力强，指导细致"
        },
        "经费情况": {
          "score": 9,
          "reason": "支持学生想法，经费无忧"
        },
        "学生补助": {
          "score": 5,
          "reason": "未提及具体补助金额"
        },
        "师生关系": {
          "score": 10,
          "reason": "超好、平易近人、无架子、女神级关怀"
        },
        "工作时间": {
          "score": 5,
          "reason": "未提及工作时间安排"
        },
        "毕业去向": {
          "score": 5,
          "reason": "未提及职业发展支持"
        },
        "overall_recommendation": "学术扎实、指导极致用心，适合希望获得全方位学术人格培养的学生"
      },
      {
        "mentor_index": 13,
        "name": "nan",
        "导师能力": {
          "score": 2,
          "reason": "无学术产出，全靠工程项目"
        },
        "经费情况": {
          "score": 7,
          "reason": "经费多但未惠及学生（不配电脑）"
        },
        "学生补助": {
          "score": 1,
          "reason": "不发月补，学生争先不去实验室"
        },
        "师生关系": {
          "score": 2,
          "reason": "团队士气低落，缺乏信任感"
        },
        "工作时间": {
          "score": 3,
          "reason": "项目驱动，隐性高强度加班"
        },
        "毕业去向": {
          "score": 3,
          "reason": "仅做到毕业，无发展支持"
        },
        "overall_recommendation": "纯项目压榨型，学术成长与职业发展均受限，强烈不推荐"
      },
      {
        "mentor_index": 14,
        "name": "李连崇",
        "导师能力": {
          "score": 8,
          "reason": "年发5篇论文+专利，科研活跃"
        },
        "经费情况": {
          "score": 9,
          "reason": "纵向横向经费富足，试验配套完善"
        },
        "学生补助": {
          "score": 7,
          "reason": "500–1000元，额外工作有奖励"
        },
        "师生关系": {
          "score": 8,
          "reason": "尊重学生、民主排名、常带吃饭"
        },
        "工作时间": {
          "score": 5,
          "reason": "强调自觉加班，弹性但强度存在"
        },
        "毕业去向": {
          "score": 8,
          "reason": "主动推荐工作、联系博后，支持到位"
        },
        "overall_recommendation": "科研产出稳定、资源充沛、就业支持强，工科务实型导师典范"
      },
      {
        "mentor_index": 15,
        "name": "喻泽红",
        "导师能力": {
          "score": 2,
          "reason": "招了不管，学术指导完全缺失"
        },
        "经费情况": {
          "score": 5,
          "reason": "未提及经费情况"
        },
        "学生补助": {
          "score": 5,
          "reason": "未提及补助情况"
        },
        "师生关系": {
          "score": 1,
          "reason": "放任自流，毫无基本师生互动"
        },
        "工作时间": {
          "score": 5,
          "reason": "未提及工作时间安排"
        },
        "毕业去向": {
          "score": 1,
          "reason": "零就业支持，自生自灭"
        },
        "overall_recommendation": "典型‘挂名导师’，学术与责任双重缺位，必须规避"
      },
      {
        "mentor_index": 16,
        "name": "刘新",
        "导师能力": {
          "score": 9,
          "reason": "国奖产出稳定，科研与就业双轨引导"
        },
        "经费情况": {
          "score": 5,
          "reason": "未提及经费细节"
        },
        "学生补助": {
          "score": 5,
          "reason": "未提及具体金额"
        },
        "师生关系": {
          "score": 10,
          "reason": "幽默靠谱，生活学习均可倾诉"
        },
        "工作时间": {
          "score": 7,
          "reason": "鼓励实习，节奏张弛有度"
        },
        "毕业去向": {
          "score": 9,
          "reason": "主动提供实习帮助与就业推荐"
        },
        "overall_recommendation": "全能型成长导师，兼顾学术卓越与职业赋能，强烈推荐"
      },
      {
        "mentor_index": 17,
        "name": "赵立业",
        "导师能力": {
          "score": 7,
          "reason": "领域内有学术影响，项目经验丰富"
        },
        "经费情况": {
          "score": 8,
          "reason": "国家+企业项目双渠道经费充足"
        },
        "学生补助": {
          "score": 4,
          "reason": "300+元，属偏低水平"
        },
        "师生关系": {
          "score": 8,
          "reason": "平等相处，关系融洽"
        },
        "工作时间": {
          "score": 7,
          "reason": "正常上班制，周末自由，较合理"
        },
        "毕业去向": {
          "score": 7,
          "reason": "多数入职大公司，前景良好"
        },
        "overall_recommendation": "稳健务实型导师，适合追求技术落地与优质就业的工科生"
      },
      {
        "mentor_index": 18,
        "name": "nan",
        "导师能力": {
          "score": 6,
          "reason": "指导节能减排项目，有耐心"
        },
        "经费情况": {
          "score": 7,
          "reason": "实验费用由导师经费报销"
        },
        "学生补助": {
          "score": 5,
          "reason": "未提及固定月补"
        },
        "师生关系": {
          "score": 9,
          "reason": "悉心指导，耐心细致"
        },
        "工作时间": {
          "score": 5,
          "reason": "未提及工作时间安排"
        },
        "毕业去向": {
          "score": 5,
          "reason": "未提及职业发展支持"
        },
        "overall_recommendation": "指导态度优秀，适合本科生科研入门或项目实践导向学生"
      },
      {
        "mentor_index": 19,
        "name": "张建宇",
        "导师能力": {
          "score": 1,
          "reason": "上课不讲内容，调离疑似因失职"
        },
        "经费情况": {
          "score": 5,
          "reason": "未提及经费情况"
        },
        "学生补助": {
          "score": 5,
          "reason": "未提及补助情况"
        },
        "师生关系": {
          "score": 1,
          "reason": "极端不负责任，违背基本师德"
        },
        "工作时间": {
          "score": 5,
          "reason": "未提及工作时间安排"
        },
        "毕业去向": {
          "score": 1,
          "reason": "无任何支持记录，声誉已受损"
        },
        "overall_recommendation": "存在严重师德问题，招生资格存疑，坚决不可选"
      },
      {
        "mentor_index": 20,
        "name": "秦勇",
        "导师能力": {
          "score": 5,
          "reason": "组年均3文，产出一般"
        },
        "经费情况": {
          "score": 7,
          "reason": "经费挺多，支撑基础研究"
        },
        "学生补助": {
          "score": 4,
          "reason": "500元且有扣钱传闻，稳定性差"
        },
        "师生关系": {
          "score": 3,
          "reason": "打卡监控、周日组会，高压控制"
        },
        "工作时间": {
          "score": 3,
          "reason": "指纹打卡+周日组会，强度过高"
        },
        "毕业去向": {
          "score": 6,
          "reason": "毕业生均就业，但无主动支持描述"
        },
        "overall_recommendation": "资源尚可但管理严苛，适合抗压强、目标就业而非学术的学生"
      }
    ]
  }
}