{
  "batch_id": 173,
  "mentors": [
    "杨达源",
    "许胤龙",
    "顾元勋",
    "苗世洪",
    "乔玉辉",
    "李文渊",
    "项炜",
    "蒋嵩山",
    "陈宝权",
    "王拴紧",
    "张骥",
    "赵长颖",
    "宋彤",
    "杨付正",
    "王永华",
    "陈立学",
    "邬荣领",
    "nan",
    "王平",
    "nan"
  ],
  "response": {
    "mentors": [
      {
        "mentor_index": 1,
        "name": "杨达源",
        "导师能力": {
          "score": 9,
          "reason": "被赞有学者之风，学术地位受认可"
        },
        "经费情况": {
          "score": 5,
          "reason": "未提及经费情况"
        },
        "学生补助": {
          "score": 5,
          "reason": "未提及学生补助"
        },
        "师生关系": {
          "score": 7,
          "reason": "被列为良师，但无具体互动描述"
        },
        "工作时间": {
          "score": 5,
          "reason": "未提及工作时间安排"
        },
        "毕业去向": {
          "score": 5,
          "reason": "未提及学生毕业去向"
        },
        "overall_recommendation": "学术声誉高，但已退休，无法指导在读生"
      },
      {
        "mentor_index": 2,
        "name": "许胤龙",
        "导师能力": {
          "score": 9,
          "reason": "组合数学权威，科研能力强"
        },
        "经费情况": {
          "score": 8,
          "reason": "副院长，经费不缺"
        },
        "学生补助": {
          "score": 5,
          "reason": "未提及具体补助金额"
        },
        "师生关系": {
          "score": 6,
          "reason": "严格但作风正派"
        },
        "工作时间": {
          "score": 5,
          "reason": "未明确说明工作强度"
        },
        "毕业去向": {
          "score": 5,
          "reason": "未提及职业发展支持"
        },
        "overall_recommendation": "学术实力强、经费充足，适合数理基础扎实者"
      },
      {
        "mentor_index": 3,
        "name": "顾元勋",
        "导师能力": {
          "score": 9,
          "reason": "被称世界首屈一指，但存夸大嫌疑"
        },
        "经费情况": {
          "score": 2,
          "reason": "基本无经费，对钱没概念"
        },
        "学生补助": {
          "score": 2,
          "reason": "基本无补助"
        },
        "师生关系": {
          "score": 8,
          "reason": "关系处理好，学生拥戴"
        },
        "工作时间": {
          "score": 4,
          "reason": "常挤出时间上思想课，隐含额外负担"
        },
        "毕业去向": {
          "score": 7,
          "reason": "称学生优秀，但无实证支持"
        },
        "overall_recommendation": "师生关系佳但资源匮乏，需谨慎评估实际培养能力"
      },
      {
        "mentor_index": 4,
        "name": "苗世洪",
        "导师能力": {
          "score": 8,
          "reason": "夯实基础+鼓励前沿创新"
        },
        "经费情况": {
          "score": 9,
          "reason": "项目充足，锻炼机会多"
        },
        "学生补助": {
          "score": 7,
          "reason": "平均水平，体恤学生"
        },
        "师生关系": {
          "score": 9,
          "reason": "尊重关心，常谈心声"
        },
        "工作时间": {
          "score": 6,
          "reason": "灵活但晚上建议来实验室"
        },
        "毕业去向": {
          "score": 9,
          "reason": "就业质量高，多入电网/设计院"
        },
        "overall_recommendation": "综合实力强、人文关怀到位，电气领域优选导师"
      },
      {
        "mentor_index": 5,
        "name": "乔玉辉",
        "导师能力": {
          "score": 3,
          "reason": "被评能力不行，无文章产出"
        },
        "经费情况": {
          "score": 9,
          "reason": "项目很多，全力支持实验"
        },
        "学生补助": {
          "score": 7,
          "reason": "固定1100元，属中上水平"
        },
        "师生关系": {
          "score": 6,
          "reason": "和蔼可亲但前提听话"
        },
        "工作时间": {
          "score": 2,
          "reason": "不分昼夜随时找人"
        },
        "毕业去向": {
          "score": 2,
          "reason": "严禁实习，毕业压力大"
        },
        "overall_recommendation": "经费足但学术指导弱，工作强度高，慎选"
      },
      {
        "mentor_index": 6,
        "name": "李文渊",
        "导师能力": {
          "score": 1,
          "reason": "差到爆，抢学生一作"
        },
        "经费情况": {
          "score": 5,
          "reason": "未提及经费情况"
        },
        "学生补助": {
          "score": 5,
          "reason": "未提及学生补助"
        },
        "师生关系": {
          "score": 0,
          "reason": "无优点，满坑爹，无师德"
        },
        "工作时间": {
          "score": 5,
          "reason": "未提及工作时间安排"
        },
        "毕业去向": {
          "score": 1,
          "reason": "无职业支持，口碑极差"
        },
        "overall_recommendation": "高风险导师，强烈不推荐"
      },
      {
        "mentor_index": 7,
        "name": "项炜",
        "导师能力": {
          "score": 5,
          "reason": "未提及科研能力"
        },
        "经费情况": {
          "score": 5,
          "reason": "未提及经费情况"
        },
        "学生补助": {
          "score": 5,
          "reason": "未提及学生补助"
        },
        "师生关系": {
          "score": 8,
          "reason": "挺好，不push，为学生考虑"
        },
        "工作时间": {
          "score": 5,
          "reason": "未提及工作时间安排"
        },
        "毕业去向": {
          "score": 5,
          "reason": "未提及职业发展支持"
        },
        "overall_recommendation": "师生关系温和，但缺乏其他维度信息，需进一步了解"
      },
      {
        "mentor_index": 8,
        "name": "蒋嵩山",
        "导师能力": {
          "score": 3,
          "reason": "课题转型失败，学术不可靠"
        },
        "经费情况": {
          "score": 2,
          "reason": "目前比较穷，项目难申请"
        },
        "学生补助": {
          "score": 2,
          "reason": "看心情发放，没钱发"
        },
        "师生关系": {
          "score": 1,
          "reason": "无师德，心眼小，侮辱学生"
        },
        "工作时间": {
          "score": 2,
          "reason": "一周休一天，晚上必须在"
        },
        "毕业去向": {
          "score": 2,
          "reason": "不允许实习，毕业靠运气"
        },
        "overall_recommendation": "存在严重师德问题，强烈避让"
      },
      {
        "mentor_index": 9,
        "name": "陈宝权",
        "导师能力": {
          "score": 8,
          "reason": "图形学/可视化大牛，国际知名"
        },
        "经费情况": {
          "score": 9,
          "reason": "大土豪，院长资源丰富"
        },
        "学生补助": {
          "score": 5,
          "reason": "多次未提具体金额"
        },
        "师生关系": {
          "score": 8,
          "reason": "亲民融洽，带学生出国参会"
        },
        "工作时间": {
          "score": 6,
          "reason": "学术抓得紧，但时间自主"
        },
        "毕业去向": {
          "score": 8,
          "reason": "BAT/MSRA等名企就业率高"
        },
        "overall_recommendation": "学术强、资源足、平台优，计算机方向优质选择"
      },
      {
        "mentor_index": 10,
        "name": "王拴紧",
        "导师能力": {
          "score": 7,
          "reason": "教科研方法与做人做事"
        },
        "经费情况": {
          "score": 5,
          "reason": "未提及经费情况"
        },
        "学生补助": {
          "score": 5,
          "reason": "未提及学生补助"
        },
        "师生关系": {
          "score": 9,
          "reason": "平易近人，始终为学生着想"
        },
        "工作时间": {
          "score": 5,
          "reason": "未提及工作时间安排"
        },
        "毕业去向": {
          "score": 5,
          "reason": "未提及职业发展支持"
        },
        "overall_recommendation": "师生关系极佳，适合重视人文指导的学生"
      },
      {
        "mentor_index": 11,
        "name": "张骥",
        "导师能力": {
          "score": 7,
          "reason": "有魅力，但未提具体学术表现"
        },
        "经费情况": {
          "score": 5,
          "reason": "未提及经费情况"
        },
        "学生补助": {
          "score": 5,
          "reason": "未提及学生补助"
        },
        "师生关系": {
          "score": 9,
          "reason": "人好，无距离感"
        },
        "工作时间": {
          "score": 5,
          "reason": "未提及工作时间安排"
        },
        "毕业去向": {
          "score": 5,
          "reason": "未提及职业发展支持"
        },
        "overall_recommendation": "师生关系友好，适合注重沟通氛围的化学方向学生"
      },
      {
        "mentor_index": 12,
        "name": "赵长颖",
        "导师能力": {
          "score": 5,
          "reason": "未提科研能力，仅提管理风格"
        },
        "经费情况": {
          "score": 5,
          "reason": "未提及经费情况"
        },
        "学生补助": {
          "score": 5,
          "reason": "未提及学生补助"
        },
        "师生关系": {
          "score": 2,
          "reason": "严厉专制，压力大"
        },
        "工作时间": {
          "score": 2,
          "reason": "延迟毕业普遍，高压管理"
        },
        "毕业去向": {
          "score": 2,
          "reason": "不允许实习，多数转行"
        },
        "overall_recommendation": "管理严苛、毕业受限，机械动力方向慎选"
      },
      {
        "mentor_index": 13,
        "name": "宋彤",
        "导师能力": {
          "score": 9,
          "reason": "性格好、水平高，惜已退休"
        },
        "经费情况": {
          "score": 5,
          "reason": "未提及经费情况"
        },
        "学生补助": {
          "score": 5,
          "reason": "未提及学生补助"
        },
        "师生关系": {
          "score": 8,
          "reason": "被高度认可，但无细节"
        },
        "工作时间": {
          "score": 5,
          "reason": "未提及工作时间安排"
        },
        "毕业去向": {
          "score": 5,
          "reason": "未提及职业发展支持"
        },
        "overall_recommendation": "学术与人格俱佳，但已退休无法招生"
      },
      {
        "mentor_index": 14,
        "name": "杨付正",
        "导师能力": {
          "score": 9,
          "reason": "学术严谨，工程能力强"
        },
        "经费情况": {
          "score": 9,
          "reason": "华为项目多，经费非常充足"
        },
        "学生补助": {
          "score": 9,
          "reason": "月均1600+水果零食，待遇优厚"
        },
        "师生关系": {
          "score": 8,
          "reason": "负责温和，氛围积极"
        },
        "工作时间": {
          "score": 7,
          "reason": "双休+弹性，下午5:30后自由"
        },
        "毕业去向": {
          "score": 9,
          "reason": "华为保底，国际会议机会多"
        },
        "overall_recommendation": "综合实力顶尖，通信方向首选导师之一"
      },
      {
        "mentor_index": 15,
        "name": "王永华",
        "导师能力": {
          "score": 3,
          "reason": "不看论文，科研全交学生"
        },
        "经费情况": {
          "score": 7,
          "reason": "经费较充足"
        },
        "学生补助": {
          "score": 4,
          "reason": "硕士200-400，博士4000（不均衡）"
        },
        "师生关系": {
          "score": 1,
          "reason": "挖苦辱骂，不尊重学生"
        },
        "工作时间": {
          "score": 1,
          "reason": "早8:30至晚10:00，无节假日"
        },
        "毕业去向": {
          "score": 1,
          "reason": "严禁实习，贬低毕业生"
        },
        "overall_recommendation": "存在严重学术放养与人格侮辱，坚决回避"
      },
      {
        "mentor_index": 16,
        "name": "陈立学",
        "导师能力": {
          "score": 8,
          "reason": "理论扎实，公式随手就来"
        },
        "经费情况": {
          "score": 9,
          "reason": "纵向经费充足，项目不愁"
        },
        "学生补助": {
          "score": 7,
          "reason": "电气学院中上水平"
        },
        "师生关系": {
          "score": 9,
          "reason": "儒雅谦和，平易近人"
        },
        "工作时间": {
          "score": 8,
          "reason": "不加班，管理宽松"
        },
        "毕业去向": {
          "score": 5,
          "reason": "未提具体就业去向"
        },
        "overall_recommendation": "学术扎实、氛围宽松，电气方向稳健型导师"
      },
      {
        "mentor_index": 17,
        "name": "邬荣领",
        "导师能力": {
          "score": 1,
          "reason": "堆砌无人引用论文，无科研产出"
        },
        "经费情况": {
          "score": 1,
          "reason": "无项目，用旧数据，设备匮乏"
        },
        "学生补助": {
          "score": 1,
          "reason": "全国最低200元"
        },
        "师生关系": {
          "score": 0,
          "reason": "当工具畜生，画饼后抛弃"
        },
        "工作时间": {
          "score": 0,
          "reason": "随叫随到，全天候打杂"
        },
        "毕业去向": {
          "score": 0,
          "reason": "无科研训练，毕业难，SCI零产出"
        },
        "overall_recommendation": "学术失职、道德失范，绝对不可选"
      },
      {
        "mentor_index": 18,
        "name": "nan",
        "导师能力": {
          "score": 5,
          "reason": "仅提读书好处，无实质信息"
        },
        "经费情况": {
          "score": 5,
          "reason": "未提及经费情况"
        },
        "学生补助": {
          "score": 5,
          "reason": "未提及学生补助"
        },
        "师生关系": {
          "score": 5,
          "reason": "未提及师生关系"
        },
        "工作时间": {
          "score": 5,
          "reason": "未提及工作时间安排"
        },
        "毕业去向": {
          "score": 5,
          "reason": "未提及职业发展支持"
        },
        "overall_recommendation": "信息完全缺失，无法评估，不建议选择"
      },
      {
        "mentor_index": 19,
        "name": "王平",
        "导师能力": {
          "score": 8,
          "reason": "光通信/半导体大牛，人均SCI"
        },
        "经费情况": {
          "score": 8,
          "reason": "经费充足，支持科研开销"
        },
        "学生补助": {
          "score": 6,
          "reason": "按学院标准，无克扣"
        },
        "师生关系": {
          "score": 7,
          "reason": "关系融洽，尊重学生"
        },
        "工作时间": {
          "score": 7,
          "reason": "不打卡，周六白天，弹性管理"
        },
        "毕业去向": {
          "score": 8,
          "reason": "腾讯百度中兴等名企实习就业多"
        },
        "overall_recommendation": "学术强、待遇稳、就业广，通信方向高性价比导师"
      }
    ]
  }
}