{
  "id": "04d85291-9738-4647-8087-0e4483d5f7d4",
  "name": "李光石",
  "school": "上海大学",
  "department": "材料科学与工程学系",
  "evaluationCount": 1,
  "totalScore": 5.0,
  "dimensionScores": {
    "导师能力": 5.0,
    "经费情况": 5.0,
    "学生补助": 5.0,
    "师生关系": 5.0,
    "工作时间": 5.0,
    "毕业去向": 5.0
  },
  "dimensionReasons": {
    "导师能力": "师资博士后，资历尚浅",
    "经费情况": "未提及经费情况",
    "学生补助": "未提及",
    "师生关系": "未提及师生互动",
    "工作时间": "未提及工作强度",
    "毕业去向": "未提及"
  },
  "overallRecommendation": "资历新，信息极少，风险较高，建议进一步核实",
  "evaluations": [
    {
      "comment": "目前为上海大学师资博士后",
      "dimensions": {}
    }
  ]
}