{
  "id": "055493b0-dd40-43c5-a5c0-84a5e746b641",
  "name": "李勇",
  "school": "清华大学",
  "department": "机械工程系",
  "evaluationCount": 8,
  "totalScore": 5.35,
  "dimensionScores": {
    "导师能力": 5.0,
    "经费情况": 5.0,
    "学生补助": 5.0,
    "师生关系": 6.25,
    "工作时间": 5.0,
    "毕业去向": 5.88
  },
  "evaluations": [
    {
      "comment": "身为李老师的学生，表示李老师绝对是为人师表的人生好导师",
      "dimensions": {}
    },
    {
      "comment": "利益相关：罗姆楼8层办公室 导师能力：很强 经费发放：经费绝对足 学生补助：完全ok 与学生关系：非常尊重学生，请学生吃饭，对学生超好 工作时间：没有强制要求，主要靠deadline和自我激励 学生毕业去向：清华前途很好",
      "dimensions": {
        "导师能力": "很强",
        "经费情况": "",
        "学生补助": "完全ok 与学生",
        "师生关系": "非常尊重学生，请学生吃饭，对学生超好 工作",
        "工作时间": "没有强制要求，主要靠deadline和自我激励 学生毕业",
        "毕业去向": "清华前途很好"
      }
    },
    {
      "comment": "李老师科研一丝不苟，教学认真严谨，对待学生一视同仁",
      "dimensions": {}
    },
    {
      "comment": "特别难得的一位好老师，严谨，务实，认真，负责。",
      "dimensions": {}
    },
    {
      "comment": "对学生非常用心！",
      "dimensions": {}
    },
    {
      "comment": "利益相关：办公室在李兆基大楼9层 导师能力：领域内知名专家，产学研结合出众 经费发放：经费充足，开展研究课题没有困难 学生补助：正常标准，不存在克扣 与学生关系：与学生关系健康良好，尊重学生个人成长，从不压榨学生 工作时间：要求工作日白天到岗，其它时间靠个人自觉，不存在打卡之类的制度 学生毕业去向：允许假期实习，毕业后主要在研究所/政府/业界发展",
      "dimensions": {
        "导师能力": "领域内知名专家，产学研结合出众",
        "经费情况": "",
        "学生补助": "正常标准，不存在克扣 与学生",
        "师生关系": "与学生",
        "工作时间": "要求工作日白天到岗，其它",
        "毕业去向": "允许假期实习，毕业后主要在研究所/政府/业界发展"
      }
    },
    {
      "comment": "李老师人好的真是没话说，对学生很用心，在业内评价也很高。为人低调务实，总是为学生着想，对于刚刚从事科研的学生来说非常适合在李老师课题组开展科研工作以及学习。",
      "dimensions": {}
    },
    {
      "comment": "李老师亦师亦友，学术上精心指导，生活上用心照料，相处几年，受益匪浅。",
      "dimensions": {}
    }
  ]
}