{
  "id": "0e1a8ecd-2a3d-4924-8f23-a940360b68ef",
  "name": "程文龙",
  "school": "中国科学技术大学",
  "department": "工程科学学院",
  "evaluationCount": 1,
  "totalScore": 8.33,
  "dimensionScores": {
    "导师能力": 9.0,
    "经费情况": 7.0,
    "学生补助": 9.0,
    "师生关系": 9.0,
    "工作时间": 8.0,
    "毕业去向": 8.0
  },
  "dimensionReasons": {
    "导师能力": "实验室发表好，国奖年年有",
    "经费情况": "只做纵向项目，稳定但类型单一",
    "学生补助": "工院13系前三，综合补助优厚",
    "师生关系": "尊重意愿，不强求，关系很好",
    "工作时间": "白天为主，晚上周末不强求",
    "毕业去向": "大多继续科研，路径清晰"
  },
  "overallRecommendation": "中科大科研型理想导师，自律者成长迅速",
  "evaluations": [
    {
      "comment": "利益相关：办公室512 导师能力：实验室文章发表情况较好，自国奖设立以来每年1-2名获奖学生 经费发放：基本只做纵向项目，很少接横向 学生补助：综合补助在工院13系里排在前三 与学生关系：与学生关系很好，老师十分尊重每一个学生的意愿，不会强求做事 工作时间：工作时间为工作日的白天，晚上和周末不强求，不过大部分同学还是自觉前来科研 学生毕业去向：毕业学生大多继续从事科研行业工作",
      "dimensions": {}
    }
  ]
}