{
  "id": "1abdd716-f585-4ae3-a18e-9f9980590b36",
  "name": "魏海坤",
  "school": "东南大学",
  "department": "自动化学院",
  "evaluationCount": 4,
  "totalScore": 7.0,
  "dimensionScores": {
    "导师能力": 6.0,
    "经费情况": 9.0,
    "学生补助": 5.0,
    "师生关系": 8.0,
    "工作时间": 6.0,
    "毕业去向": 8.0
  },
  "dimensionReasons": {
    "导师能力": "工程项目出众，能力尚可但不出色",
    "经费情况": "全院最高经费，福利丰富",
    "学生补助": "未提具体金额，仅称有福利",
    "师生关系": "为人谦和，关系没的说",
    "工作时间": "忙但愿指导，允许实习，管理宽松",
    "毕业去向": "就业管得不严，去阿里腾讯等"
  },
  "overallRecommendation": "工程实践强、经费足、就业支持好，推荐",
  "evaluations": [
    {
      "comment": "导师能力：请问这位老师怎么样呀 经费发放：有知道的嘛",
      "dimensions": {}
    },
    {
      "comment": "导师能力：工程项目比较出众 经费发放：经费还是比较足的，有各种福利！！ 与学生关系：与学生关系没的说，为人谦和，平时很忙，但是愿意指导你 学生毕业去向：允许实习，硕士就业管的不严，自己看书，工作不错，博士方向挺好，就业不太清楚",
      "dimensions": {}
    },
    {
      "comment": "导师能力：不知道为何魏老师的评价都被删除了，老魏导师能力还是可以的，但算不上出色 经费发放：全院最高经费！没得说 与学生关系：和大部分学生关系都挺好的 学生毕业去向：还是挺好的，有去阿里、腾讯的",
      "dimensions": {}
    },
    {
      "comment": "导师能力：不知道为何魏老师的评价都被删除了，老魏导师能力还是可以的，但算不上出色",
      "dimensions": {}
    }
  ]
}