{
  "id": "23e0a5c3-8018-4e4d-a0f8-5a6975354338",
  "name": "杨奇",
  "school": "华中科技大学",
  "department": "光学与电子信息学院",
  "evaluationCount": 1,
  "totalScore": 8.0,
  "dimensionScores": {
    "导师能力": 9.0,
    "经费情况": 9.0,
    "学生补助": 7.0,
    "师生关系": 9.0,
    "工作时间": 5.0,
    "毕业去向": 9.0
  },
  "dimensionReasons": {
    "导师能力": "学术地位高，不抢一作，指导开明",
    "经费情况": "项目多，经费充足",
    "学生补助": "光电院正常水平，不克扣，保障到位",
    "师生关系": "对学生很好，易相处，尊重学术贡献",
    "工作时间": "未提及具体工作强度",
    "毕业去向": "业内人脉广，学术与就业双通道支持"
  },
  "overallRecommendation": "学术实力、资源、人品、职业支持俱佳，属理想型导师。",
  "evaluations": [
    {
      "comment": "利益相关：南五321 导师能力：导师能力高，在学术界有一定地位 经费发放：项目多，经费充足 学生补助：和其他老师一样，光电院正常水平，不会克扣 与学生关系：不会抢论文一作，对学生很好，人也很好相处 学生毕业去向：老师在业内人脉广泛，工作或者搞学术都能有很好的发展",
      "dimensions": {}
    }
  ]
}