{
  "id": "2c6d8cc4-15cf-42be-8d3a-a8683aaa1ab0",
  "name": "鲜　斌",
  "school": "天津大学",
  "department": "电气与自动化工程学院",
  "evaluationCount": 3,
  "totalScore": 6.5,
  "dimensionScores": {
    "导师能力": 7.0,
    "经费情况": 5.0,
    "学生补助": 4.0,
    "师生关系": 7.0,
    "工作时间": 8.0,
    "毕业去向": 8.0
  },
  "dimensionReasons": {
    "导师能力": "提供方向，改论文认真，较务实",
    "经费情况": "经费不多，仅够维持实验室运转",
    "学生补助": "仅200元，明显低于合理水平",
    "师生关系": "宽松包容，达标即可，关系平和",
    "工作时间": "时间自由，例会极少，压力小",
    "毕业去向": "主动安排实习，为学生着想"
  },
  "overallRecommendation": "温和务实型导师，适合求稳、重实践的学生",
  "evaluations": [
    {
      "comment": "利益相关：XXX，在不在实(si)验室(si)呀？过来一趟～ 导师能力：给学生提供大体研究方向，改论文比较认真。 经费发放：经费不多，刚好维持实验室正常用度 学生补助：200 与学生关系：只要够学校毕业要求就可以～ 工作时间：时间自由，例会很少。 学生毕业去向：给安排实习，比较为学生着想。",
      "dimensions": {}
    },
    {
      "comment": "最近开始走卖萌路线 不知道是疯了还是怎么的",
      "dimensions": {}
    },
    {
      "comment": "人不错 就是最近穷 听说以前有钱时也哗哗的发 最近没见了",
      "dimensions": {}
    }
  ]
}