{
  "id": "2fa1f2e9-70cd-48ff-a0d2-67b081e415ae",
  "name": "薛若军",
  "school": "哈尔滨工程大学",
  "department": "核科学与技术学院",
  "evaluationCount": 1,
  "totalScore": 5.0,
  "dimensionScores": {
    "导师能力": 5.0,
    "经费情况": 5.0,
    "师生关系": 5.0,
    "毕业去向": 5.0
  },
  "evaluations": [
    {
      "comment": "导师能力：年龄不小却刚刚博士毕业 经费发放：基本没有啥经费，全靠自学 与学生关系：非常喜欢让学生，批卷子，核对分数，批改作业，帮孩子做作业，接孩子，带孩子玩儿，各个方面杂活儿基本干不完，还不尊重你的时间 学生毕业去向：工作基本靠自己找",
      "dimensions": {
        "导师能力": "年龄不小却刚刚博士毕业",
        "经费情况": "基本没有啥",
        "师生关系": "非常喜欢让学生，批卷子，核对分数，批改作业，帮孩子做作业，接孩子，带孩子玩儿，各个方面杂活儿基本干不完，还不尊重你的",
        "毕业去向": "工作基本靠自己找"
      }
    }
  ]
}