{
  "id": "3f75e4ac-0d53-4948-bf85-741ce1923c8c",
  "name": "高伟清",
  "school": "合肥工业大学",
  "department": "电子科学与应用物理学院",
  "evaluationCount": 2,
  "totalScore": 5.88,
  "dimensionScores": {
    "导师能力": 5.0,
    "师生关系": 6.75,
    "经费情况": 6.75,
    "学生补助": 5.0,
    "工作时间": 5.0,
    "毕业去向": 6.75
  },
  "evaluations": [
    {
      "comment": "导师能力：水平当然够，反正知道研究生完全没问题。 与学生关系：不抢一作，尊重学生",
      "dimensions": {
        "导师能力": "水平当然够，反正知道研究生完全没问题。 与学生",
        "师生关系": "不抢一作，尊重学生"
      }
    },
    {
      "comment": "利益相关：高伟清，男，安徽庐江人，1979年6月生，博士，教授，硕士生导师。2000年毕业于南开大学物理系应用物理专业，获理学学士学位；2003年毕业于南开大学现代光学研究所光学专业，获理学硕士学位；2007年毕业于中国科学技术大学物理系光学专业，获理学博士学位。2007年7月进入合肥工业大学工作；2010年7月赴日本丰田工业大学先进光子技术研究中心从事博士后研究；2013年7月回国并调入合肥工业大学电子科学与应用物理学院工作。获2013-2014年度合肥工业大学“三育人”先进工作者称号。 导师能力：近年来主要从事光纤激光器及光纤非线性效应方面的研究工作，包括光纤受激布里渊激光器、光纤受激拉曼激光器、被动锁模光纤激光器、光纤超连续谱产生、光纤三次谐波产生和光纤四波混频效应等。自2010年以来，共发表SCI索引期刊论文50多篇，其中第一作者或通讯作者论文17篇，全部期刊论文在SCI检索中总引超过440次，他引超过380次。此外，自2010年以来，共发表EI索引论文50多篇，其中第一作者或通讯作者论文20多篇。 经费发放：主持国家自然科学基金青年基金一项，主持国家自然科学基金面上项目一项，主持主持中央高校改善基本办学条件专项资金一项。 学生补助：不定。 与学生关系：尊重学生，论文不抢一作，为人正直。 工作时间：正常工作时间，不要求加班。 学生毕业去向：推荐读博，允许实习，学生前景都很好！",
      "dimensions": {
        "导师能力": "近年来主要从事光纤激光器及光纤非线性效应方面的研究工作，包括光纤受激布里渊激光器、光纤受激拉曼激光器、被动锁模光纤激光器、光纤超连续谱产生、光纤三次谐波产生和光纤四波混频效应等。自2010年以来，共发表SCI索引期刊论文50多篇，其中第一作者或通讯作者论文17篇，全部期刊论文在SCI检索中总引超过440次，他引超过380次。此外，自2010年以来，共发表EI索引论文50多篇，其中第一作者或通讯作者论文20多篇。",
        "经费情况": "主持国家自然科学基金青年基金一项，主持国家自然科学基金面上项目一项，主持主持中央高校改善基本办学条件专项资金一项。 学生",
        "学生补助": "不定。 与学生",
        "师生关系": "尊重学生，论文不抢一作，为人正直。 工作",
        "工作时间": "正常工作",
        "毕业去向": "推荐读博，允许实习，学生前景都很好！"
      }
    }
  ]
}