{
  "id": "533adecd-6749-4c52-b524-6de3d19cdf20",
  "name": "徐明伟",
  "school": "清华大学",
  "department": "计算机科学与技术系",
  "evaluationCount": 6,
  "totalScore": 5.0,
  "dimensionScores": {
    "导师能力": 5.0
  },
  "evaluations": [
    {
      "comment": "很好的老师，为学生着想，对学生平等尊重，很有师德。略小气～",
      "dimensions": {}
    },
    {
      "comment": "除了抠，确实是抠到死，其他都很好，不过好老师，不发钱也无所谓",
      "dimensions": {}
    },
    {
      "comment": "对学生很不错的老师，尊重学生。自身导师能力也不错。不过感觉对学生管的有些松。",
      "dimensions": {}
    },
    {
      "comment": "导师能力：都是这两年的评价。。。各位师兄师姐，我可能还认识你们。。。说帮主抠门，你们还真是亲学生",
      "dimensions": {
        "导师能力": "都是这两年的评价。。。各位师兄师姐，我可能还认识你们。。。说帮主抠门，你们还真是亲学生"
      }
    },
    {
      "comment": "除了方向以外，其他好的不能再好。",
      "dimensions": {}
    },
    {
      "comment": "和蔼可亲，虽然抠门了点，但是对学生极好！",
      "dimensions": {}
    }
  ]
}