{
  "id": "594fd7f6-b93a-4b8a-a1f7-4431589401a9",
  "name": "陈志平",
  "school": "浙江大学",
  "department": "能源工程学系",
  "evaluationCount": 1,
  "totalScore": 5.0,
  "dimensionScores": {
    "导师能力": 5.0,
    "经费情况": 5.0,
    "师生关系": 5.0,
    "毕业去向": 5.0
  },
  "evaluations": [
    {
      "comment": "导师能力：储罐方向的科研吧，都是学生自己科研，导师已经不做研究了 经费发放：经费还是挺充足的 与学生关系：一般，研一研二都在搬砖。。后面的时间才开始做科研 学生毕业去向：不允许实习，毕业后发展看个人",
      "dimensions": {
        "导师能力": "储罐方向的科研吧，都是学生自己科研，导师已经不做研究了",
        "经费情况": "",
        "师生关系": "一般，研一研二都在搬砖。。后面的",
        "毕业去向": "不允许实习，毕业后发展看个人"
      }
    }
  ]
}