{
  "id": "5e307896-e29a-46f7-b18d-70295f9dabf1",
  "name": "杜方",
  "school": "宁夏大学",
  "department": "数学计算机学院",
  "evaluationCount": 1,
  "totalScore": 4.71,
  "dimensionScores": {
    "导师能力": 5.0,
    "经费情况": 5.0,
    "学生补助": 5.0,
    "师生关系": 3.25,
    "工作时间": 5.0,
    "毕业去向": 5.0
  },
  "evaluations": [
    {
      "comment": "利益相关：目前宁大B区信息学院教授 导师能力：美国常青藤大学归国 经费发放：2015年国家自然基金申请者 学生补助：学期末会发1000多元钱 与学生关系：无琐事，无杂活 工作时间：每周五天工作时间 学生毕业去向：出国留学及自主就业",
      "dimensions": {
        "导师能力": "美国常青藤大学归国",
        "经费情况": "2015年国家自然基金申请者 学生",
        "学生补助": "学期末会发1000多元钱 与学生",
        "师生关系": "无琐事，无杂活 工作",
        "工作时间": "每周五天工作",
        "毕业去向": "出国留学及自主就业"
      }
    }
  ]
}