{
  "id": "6134888f-48a7-45c9-b9bf-0a785625777e",
  "name": "全涌",
  "school": "同济大学",
  "department": "土木工程学院",
  "evaluationCount": 2,
  "totalScore": 4.71,
  "dimensionScores": {
    "导师能力": 5.88,
    "经费情况": 4.12,
    "学生补助": 4.12,
    "师生关系": 4.12,
    "毕业去向": 5.0,
    "工作时间": 5.0
  },
  "evaluations": [
    {
      "comment": "利益相关：风工程馆 导师能力：博士毕业时为最高水平，现在都在灌水 经费发放：比较少 学生补助：做项目 与学生关系：利用做项目关系 学生毕业去向：基本没前途",
      "dimensions": {
        "导师能力": "博士毕业时为最高水平，现在都在灌水",
        "经费情况": "比较少 学生",
        "学生补助": "做项目 与学生",
        "师生关系": "利用做项目",
        "毕业去向": "基本没前途"
      }
    },
    {
      "comment": "利益相关：办公室风工程馆 导师能力：灌水，不怎么样 经费发放：不知道 学生补助：很少，而且经常不发 与学生关系：天天监视学生，星期天和国定假期也来监视，每天打卡上班 没有良心，经常斥责学生，经常逼着学生做项目，非常恶毒 典型“无良导师” 工作时间：周末和假期经常加班 学生毕业去向：风工程很难找工作的，别入坑，导师又不怎么样",
      "dimensions": {
        "导师能力": "灌水，不怎么样",
        "经费情况": "不知道 学生",
        "学生补助": "很少，而且经常不发 与学生",
        "师生关系": "天天监视学生，星期天和国定假期也来监视，每天打卡上班 没有良心，经常斥责学生，经常逼着学生做项目，非常恶毒 典型“无良导师” 工作",
        "工作时间": "周末和假期经常加班 学生毕业",
        "毕业去向": "风工程很难找工作的，别入坑，导师又不怎么样"
      }
    }
  ]
}