{
  "id": "6a2f56d9-9989-43cb-9309-41243d02c2d0",
  "name": "刘昱",
  "school": "未知",
  "department": "微电子研究所",
  "evaluationCount": 1,
  "totalScore": 4.56,
  "dimensionScores": {
    "导师能力": 3.25,
    "经费情况": 5.0,
    "师生关系": 5.0,
    "毕业去向": 5.0
  },
  "evaluations": [
    {
      "comment": "导师能力：只能说相当厉害了，千人计划引进学者，沉迷科研无法自拔 经费发放：经费看运气吧，本来说让我做一个跟新加坡的项目的，结果没谈成，就自己做项目了，但是集成电路啥的我不太懂，项目很多，博士和硕士也很多 与学生关系：实验室管理很宽松，只要你别违反大环境的时间表，如果你有想法，老师也支持 学生毕业去向：不允许实习，毕竟中科院，很多转博的学生转到刘老师名下，做硬件应该挺厉害的，老师属于很绅士没架子的那种",
      "dimensions": {
        "导师能力": "只能说相当厉害了，千人计划引进学者，沉迷科研无法自拔",
        "经费情况": "",
        "师生关系": "实验室管理很宽松，只要你别违反大环境的",
        "毕业去向": "不允许实习，毕竟中科院，很多转博的学生转到刘老师名下，做硬件应该挺厉害的，老师属于很绅士没架子的那种"
      }
    }
  ]
}