{
  "id": "6feb9fef-918c-4231-8a50-d4181b7278a8",
  "name": "段峰",
  "school": "南开大学",
  "department": "计算机与控制工程学院",
  "evaluationCount": 1,
  "totalScore": 6.17,
  "dimensionScores": {
    "导师能力": 7.0,
    "经费情况": 5.0,
    "学生补助": 5.0,
    "师生关系": 8.0,
    "工作时间": 5.0,
    "毕业去向": 7.0
  },
  "dimensionReasons": {
    "导师能力": "‘很为学生着想’反映责任心与指导意识",
    "经费情况": "未提及，按中立处理",
    "学生补助": "未提及，按中立处理",
    "师生关系": "着想即尊重与主动关怀",
    "工作时间": "未提及，按中立处理",
    "毕业去向": "着想隐含对毕业与发展关注"
  },
  "overallRecommendation": "责任导向型导师，适合需要情感支持与方向引导的学生",
  "evaluations": [
    {
      "comment": "很为学生着想的老师",
      "dimensions": {}
    }
  ]
}