{
  "id": "82ffe6e1-6ec4-4ea1-a2f5-cb107752e8cc",
  "name": "唐杰",
  "school": "清华大学",
  "department": "计算机科学与技术系",
  "evaluationCount": 2,
  "totalScore": 7.5,
  "dimensionScores": {
    "导师能力": 7.0,
    "经费情况": 10.0,
    "学生补助": 9.0,
    "师生关系": 6.0,
    "工作时间": 5.0,
    "毕业去向": 8.0
  },
  "dimensionReasons": {
    "导师能力": "曾很强，现略滞后但仍有底蕴",
    "经费情况": "经费非常充足，学生钱充裕",
    "学生补助": "学生资金充裕",
    "师生关系": "push但不安排杂活，偶不尊重",
    "工作时间": "push隐含强度大，但未明确加班",
    "毕业去向": "去向好，但限制实习"
  },
  "overallRecommendation": "资源雄厚但管理高压，适合目标明确、抗压强的学生",
  "evaluations": [
    {
      "comment": "唐总很nice，经常跟学生交流。但是比较push。",
      "dimensions": {}
    },
    {
      "comment": "导师能力：之前很牛叉，但是现在貌似有些落后，事情多，学生有点管不过来，而且比较自负 经费发放：经费非常充足，学生的钱也很充裕 与学生关系：比较push，有时可能会不太尊重学生，不过不会安排杂活 学生毕业去向：学生出入大都不错，一般不会允许实习",
      "dimensions": {}
    }
  ]
}