{
  "id": "8da2f23c-9e1e-4e49-a43e-7e2cf2a64373",
  "name": "牛景阳",
  "school": "河南大学",
  "department": "化学",
  "evaluationCount": 1,
  "totalScore": 6.0,
  "dimensionScores": {
    "导师能力": 9.0,
    "经费情况": 5.0,
    "学生补助": 5.0,
    "师生关系": 7.0,
    "工作时间": 5.0,
    "毕业去向": 5.0
  },
  "dimensionReasons": {
    "导师能力": "河南省特聘教授，多酸化学领域知名专家",
    "经费情况": "未提及经费情况",
    "学生补助": "未提及学生补助",
    "师生关系": "评价为‘不错的好导师’，隐含尊重",
    "工作时间": "未提及工作时间",
    "毕业去向": "未提及毕业去向"
  },
  "overallRecommendation": "学术声誉高，师生关系良好，但信息有限需进一步核实。",
  "evaluations": [
    {
      "comment": "牛老师作为河南省特聘教授，在多酸化学领域享有盛名，拥有不错的科研成果。是一个不错的好导师。",
      "dimensions": {}
    }
  ]
}