{
  "id": "998e50b8-a08b-466a-ad03-8992f897668b",
  "name": "申迎华",
  "school": "太原理工大学",
  "department": "化学化工学院",
  "evaluationCount": 1,
  "totalScore": 5.0,
  "dimensionScores": {
    "导师能力": 5.0,
    "学生补助": 5.0,
    "师生关系": 5.0,
    "工作时间": 5.0,
    "毕业去向": 5.0
  },
  "evaluations": [
    {
      "comment": "导师能力：导师不看文献，研究生方向都难定 学生补助：几乎没有 与学生关系：琐事一箩筐 工作时间：忙时周六日加班 学生毕业去向：不能实现，找工作时间都有限",
      "dimensions": {
        "导师能力": "导师不看文献，研究生方向都难定 学生",
        "学生补助": "几乎没有 与学生",
        "师生关系": "琐事一箩筐 工作",
        "工作时间": "忙时周六日加班 学生毕业",
        "毕业去向": "不能实现，找工作"
      }
    }
  ]
}