{
  "id": "9db4a3b2-e070-4f36-a7a1-456fd1bf7e59",
  "name": "李晓辉",
  "school": "陕西师范大学",
  "department": "物理学与信息技术学院",
  "evaluationCount": 7,
  "totalScore": 2.17,
  "dimensionScores": {
    "导师能力": 5.0,
    "经费情况": 3.0,
    "学生补助": 1.0,
    "师生关系": 1.0,
    "工作时间": 1.0,
    "毕业去向": 2.0
  },
  "dimensionReasons": {
    "导师能力": "严苛但不教，指导缺位",
    "经费情况": "经费少且不报销，套奖学金",
    "学生补助": "补助为0，克扣严重",
    "师生关系": "师大大煞，精神压迫明显",
    "工作时间": "全天夺命call，无休止加班",
    "毕业去向": "禁止找工作，毕业威胁常态化"
  },
  "overallRecommendation": "绝对回避：高压压榨型，身心健康与职业发展双重高危",
  "evaluations": [
    {
      "comment": "学生毕业去向：只说两点 不让找工作，以毕业威胁。 对学生不负责，还要结果。",
      "dimensions": {}
    },
    {
      "comment": "李老师对学生要求严格，是对学生负责任，自己每天工作很长时间，周六日也到实验室加班，这种对待科研的态度值得我们敬仰！",
      "dimensions": {}
    },
    {
      "comment": "要求专硕学生两篇sci，学硕3篇sci。否则不能毕业。 专硕临近毕业不让找工作。发文章必须2区以上。而且啥都不教。就这几条，谁敢跟他读我服你。",
      "dimensions": {}
    },
    {
      "comment": "李“大牛”在学院很著名。据说，一天24小时随时给学生打电话，经常半夜给学生发消息。一周七天，没有假期，任何人不到自习室，立马夺命call。学校要求任何一篇文章就能毕业。李“大牛”要求3篇2区sci，注意，会议论文不算，专利不算。达不到要求等着延期吧，而且听说从不带学生，问他啥也不教，也不让学生出去找工作。",
      "dimensions": {}
    },
    {
      "comment": "利益相关：陕西师范大学致知楼3444 导师能力：还行吧 经费发放：套现 学生补助：0 与学生关系：烂的掉渣 工作时间：全天夺命call 学生毕业去向：没有任何前途，迟早出现跳楼的。",
      "dimensions": {}
    },
    {
      "comment": "导师能力：个人水平还行 经费发放：经费少，且学生一分钱也别想报销，不套你的奖学金你就烧高香吧 与学生关系：号称“师大大煞”，你懂的 学生毕业去向：没有任何前途，不让你找工作，不让你准备读博，你安心坐坐实验吧，他说你这没创新，你看看文献吧，他说你就会看文献，不动手能会么？你再去做实验，他说你啥也不会就敢来做实验？以此类推，重复到你毕业",
      "dimensions": {}
    },
    {
      "comment": "鄙视这种压榨学生的“大牛”，想有个好前途，想有个好人生的就抓紧时间绕道吧。",
      "dimensions": {}
    }
  ]
}