{
  "id": "9dbdadbb-c2bd-4116-bf95-5a6bf221d9a6",
  "name": "佃松宜",
  "school": "四川大学",
  "department": "电气信息学院",
  "evaluationCount": 1,
  "totalScore": 1.33,
  "dimensionScores": {
    "导师能力": 1.0,
    "经费情况": 2.0,
    "学生补助": 1.0,
    "师生关系": 0.0,
    "工作时间": 2.0,
    "毕业去向": 2.0
  },
  "dimensionReasons": {
    "导师能力": "‘几乎没有学术’，长期在外开公司",
    "经费情况": "有经费也不给学生，挪用嫌疑明显",
    "学生补助": "工资极低+当面辱骂，零基本保障",
    "师生关系": "辱骂、压榨、强迫实习，严重失德",
    "工作时间": "熬夜做+不管不问，管理混乱无序",
    "毕业去向": "只能进其公司，职业路径被垄断"
  },
  "overallRecommendation": "师德严重失范，涉嫌违法用工，绝对不可选",
  "evaluations": [
    {
      "comment": "利益相关：基础B208A 自动化系主任 导师能力：几乎没有学术 学校里很难见到人 自己在外边开公司 经费发放：有经费也不会给学生 学生补助：不可能有补助 与学生关系：压榨学生去他公司实习 给的工资极低 当面辱骂学生 工作时间：有事的时候熬夜做 没事的时候不管不问 学生毕业去向：很难自己去实习 一般只能去他公司实习",
      "dimensions": {}
    }
  ]
}