{
  "id": "abf42563-f4c4-43cc-ba6d-7b3aa429ed49",
  "name": "李东升",
  "school": "浙江大学",
  "department": "材料科学与工程学系",
  "evaluationCount": 1,
  "totalScore": 6.33,
  "dimensionScores": {
    "导师能力": 8.0,
    "经费情况": 5.0,
    "学生补助": 5.0,
    "师生关系": 9.0,
    "工作时间": 5.0,
    "毕业去向": 6.0
  },
  "dimensionReasons": {
    "导师能力": "认真负责、因材施教",
    "经费情况": "未提及经费情况",
    "学生补助": "未提及补助情况",
    "师生关系": "体谅基础弱，安排易课题",
    "工作时间": "未提及工作强度",
    "毕业去向": "未提但态度积极"
  },
  "overallRecommendation": "责任心强、关怀学生，适合基础薄弱者",
  "evaluations": [
    {
      "comment": "学生毕业去向：我跨考过来，李老师知道我专业基础知识不是很好，给我安排的课题也相对容易点，老师认真负责",
      "dimensions": {}
    }
  ]
}