{
  "id": "b0819a2e-b71c-4e8e-ace1-344875c56c46",
  "name": "郭一楠",
  "school": "中国矿业大学(江苏)",
  "department": "信息与电气工程学院",
  "evaluationCount": 1,
  "totalScore": 5.83,
  "dimensionScores": {
    "导师能力": 7.0,
    "经费情况": 5.0,
    "学生补助": 5.0,
    "师生关系": 8.0,
    "工作时间": 5.0,
    "毕业去向": 5.0
  },
  "dimensionReasons": {
    "导师能力": "本科授课认真负责，山西籍，口碑正面",
    "经费情况": "未提及科研经费",
    "学生补助": "未提及",
    "师生关系": "真诚、爱笑、认真负责，本科反馈积极",
    "工作时间": "未提及工作强度",
    "毕业去向": "未提及就业支持"
  },
  "overallRecommendation": "本科教学口碑佳，但研究生指导信息不足，需进一步验证",
  "evaluations": [
    {
      "comment": "利益相关：本科阶段在矿大上过郭老师的过程控制，她是山西人。人很好，对待学生真诚认真负责，爱笑爱说。推荐报名。其他方面不了解，就不评价了",
      "dimensions": {}
    }
  ]
}