{
  "id": "bff3f28c-24cb-4a96-982b-a7273eb40786",
  "name": "徐坚",
  "school": NaN,
  "department": "化学研究所",
  "evaluationCount": 1,
  "totalScore": 5.0,
  "dimensionScores": {
    "经费情况": 5.0,
    "学生补助": 5.0,
    "师生关系": 5.0,
    "工作时间": 5.0,
    "毕业去向": 5.0
  },
  "evaluations": [
    {
      "comment": "利益相关：话多 经费发放：富得流油 学生补助：按顶配发工资 与学生关系：碰见第一个不用扶门、拎包、取快递的老师 工作时间：工作时间任意，化学所有自觉加班的气氛 学生毕业去向：对学生出路还是很关照的",
      "dimensions": {
        "经费情况": "富得流油 学生",
        "学生补助": "按顶配发工资 与学生",
        "师生关系": "碰见第一个不用扶门、拎包、取快递的老师 工作",
        "工作时间": "工作",
        "毕业去向": "对学生出路还是很关照的"
      }
    }
  ]
}