{
  "id": "d15b587e-c0ce-44fb-86db-a1012d9c5617",
  "name": "赵亦工",
  "school": "西安电子科大",
  "department": "电子工程学院",
  "evaluationCount": 1,
  "totalScore": 2.5,
  "dimensionScores": {
    "导师能力": 2.0,
    "经费情况": 2.0,
    "学生补助": 5.0,
    "师生关系": 2.0,
    "工作时间": 3.0,
    "毕业去向": 1.0
  },
  "dimensionReasons": {
    "导师能力": "被指误人子弟、无科研产出",
    "经费情况": "没项目，混吃等死",
    "学生补助": "未提及",
    "师生关系": "学生闻之躲避，关系极差",
    "工作时间": "随叫随到，隐性高压",
    "毕业去向": "做的东西无法找工作，意义存疑"
  },
  "overallRecommendation": "多项负面实锤，强烈不建议报考",
  "evaluations": [
    {
      "comment": "利益相关：人称赵义工，教过矩阵论 导师能力：导师能力基本没有，完全误人子弟。不见他发啥文章啊。 经费发放：没项目，混吃等死的那种。科研就更不能提了。 学生补助：这题不会，下一道吧。 与学生关系：听见这个名字大家都躲，这有不明情况的外校学生会读他的研究生。 工作时间：平时不加班，随叫随到才是最狠的。 学生毕业去向：做的东西完全无法找到工作，都不知道有何意义。",
      "dimensions": {}
    }
  ]
}