{
  "id": "e6bd2537-a490-4b8a-914a-f5c1c8101a38",
  "name": NaN,
  "school": NaN,
  "department": NaN,
  "evaluationCount": 2,
  "totalScore": 4.58,
  "dimensionScores": {
    "导师能力": 5.0,
    "经费情况": 5.0,
    "学生补助": 5.0,
    "师生关系": 2.5,
    "工作时间": 5.0,
    "毕业去向": 5.0
  },
  "evaluations": [
    {
      "comment": "陈芝麻烂谷子的背后讲人坏话是真的",
      "dimensions": {}
    },
    {
      "comment": "利益相关：土木楼b411 浙江台州人 导师能力：年龄比较大了，基本上没啥进取心，工作日没有会议啥的也是来得晚，到点就走 经费发放：一般吧，混的久了纵向课题钱还算有 学生补助：大部分没有，打杂多的有 与学生关系：硕士生不错，老师不管。博士很坑，文章贼少，而且老师的观点不能忤逆，很不理解学生，男博士普遍打杂多，毕业时间还晚，他在背后几乎说过每一个他自己的学生的坏话，学生过得比较痛苦 工作时间：不加班，但是毕业不早 学生毕业去向：不允许实习，硕士一般偷偷去。博士毕业时间基本都5年上，而且文章少，留高校的屈指可数。基本都去地产了",
      "dimensions": {
        "导师能力": "年龄比较大了，基本上没啥进取心，工作日没有会议啥的也是来得晚，到点就走",
        "经费情况": "一般吧，混的久了纵向课题钱还算有 学生",
        "学生补助": "大部分没有，打杂多的有 与学生",
        "师生关系": "硕士生不错，老师不管。博士很坑，文章贼少，而且老师的观点不能忤逆，很不理解学生，男博士普遍打杂多，毕业",
        "工作时间": "不加班，但是毕业不早 学生毕业",
        "毕业去向": "不允许实习，硕士一般偷偷去。博士毕业"
      }
    }
  ]
}