{
  "id": "e829f49a-6e44-499f-8741-f4f5acbe17ce",
  "name": NaN,
  "school": NaN,
  "department": NaN,
  "evaluationCount": 3,
  "totalScore": 5.53,
  "dimensionScores": {
    "导师能力": 5.0,
    "经费情况": 5.0,
    "学生补助": 6.42,
    "师生关系": 6.17,
    "工作时间": 4.42,
    "毕业去向": 6.17
  },
  "evaluations": [
    {
      "comment": "利益相关：蒙民伟科技大楼北楼N1008 导师能力：曹老师导师能力一流，坚持基础研究和实际应用并重，跟着曹老师做科研既能领略学术前沿的风采又能看到应用落地的曙光 经费发放：纵向经费充足，有少量横向课题，主要是以做出有意义的成果+学生得到锻炼为主 学生补助：高于平均值，而且过节都会有聚餐，实验室氛围很好 与学生关系：与学生关系很好，曹爹以身作则，是我们的榜样和楷模；对学生以尊重和鼓励，堪称良师益友。 工作时间：要求硕士生每天至少工作八小时，周末不加班，不会严格打卡，总体靠自觉。 学生毕业去向：充分理解尊重学生的不同职业选择和个性发展，鼓励大家到各行各业发光发热。",
      "dimensions": {
        "导师能力": "曹老师",
        "经费情况": "纵向",
        "学生补助": "高于平均值，而且过节都会有聚餐，实验室氛围很好 与学生",
        "师生关系": "与学生",
        "工作时间": "要求硕士生每天至少工作八小时，周末不加班，不会严格打卡，总体靠自觉。 学生毕业",
        "毕业去向": "充分理解尊重学生的不同职业选择和个性发展，鼓励大家到各行各业发光发热。"
      }
    },
    {
      "comment": "导师能力：导师能力不错 经费发放：经费发放一般，没有大老板支持 学生补助：中等 与学生关系：老师为人极好 为学生着想 工作时间：周末休息 平时没有硬性要求 学生毕业去向：发几篇好文章搞学术还可以 不搞学术去企业也有希望",
      "dimensions": {
        "导师能力": "",
        "经费情况": "",
        "学生补助": "中等 与学生",
        "师生关系": "老师为人极好 为学生着想 工作",
        "工作时间": "周末休息 平时没有硬性要求 学生毕业",
        "毕业去向": "发几篇好文章搞学术还可以 不搞学术去企业也有希望"
      }
    },
    {
      "comment": "利益相关：蒙民伟科技大楼 导师能力：导师能力非常高，常年和学生工作在一线 经费发放：纵向经费充足，足够支持基础科学研究； 有少量横向课题，可以帮助学生锻炼解决实际问题的能力 学生补助：相比较高 与学生关系：给学生充分的探索空间，及时和学生谈论课题进度，帮助学生修改论文非常及时；努力帮助学生解决实际生活中的困难。 工作时间：保证课题进度基础上，工作时间自由 学生毕业去向：鼓励学生参与就业相关的实习，鼓励学生多元发展",
      "dimensions": {
        "导师能力": "",
        "经费情况": "纵向",
        "学生补助": "相比较高 与学生",
        "师生关系": "给学生充分的探索空间，及时和学生谈论课题进度，帮助学生修改论文非常及时；努力帮助学生解决实际生活中的困难。 工作",
        "工作时间": "保证课题进度基础上，工作",
        "毕业去向": "鼓励学生参与就业相关的实习，鼓励学生多元发展"
      }
    }
  ]
}