{
  "id": "ebb06f9b-51db-4139-b5f2-b05c5442adce",
  "name": "未知导师",
  "school": "未知学校",
  "department": "未知院系",
  "evaluationCount": 2,
  "totalScore": 5.67,
  "dimensionScores": {
    "导师能力": 7.0,
    "经费情况": 7.0,
    "学生补助": 5.0,
    "师生关系": 5.0,
    "工作时间": 5.0,
    "毕业去向": 5.0
  },
  "dimensionReasons": {
    "导师能力": "院长身份+液压领域公认实力",
    "经费情况": "机电系主任，项目资源应较充足",
    "学生补助": "未提及补助情况",
    "师生关系": "非其学生，无直接关系评价",
    "工作时间": "未提及工作强度",
    "毕业去向": "未提及毕业支持"
  },
  "overallRecommendation": "行政与学术双强，但缺乏学生视角评价，需进一步核实。",
  "evaluations": [
    {
      "comment": "权老师是院长，虽然我不是权老师的学生，但知道权老师学术很厉害。",
      "dimensions": {}
    },
    {
      "comment": "液压方面有几把刷子。机电系主任。",
      "dimensions": {}
    }
  ]
}