{
  "id": "ecac4735-6978-4365-92ba-7dcfc0979dd4",
  "name": "未知导师",
  "school": "未知学校",
  "department": "未知院系",
  "evaluationCount": 1,
  "totalScore": 5.83,
  "dimensionScores": {
    "导师能力": 6.0,
    "经费情况": 7.0,
    "学生补助": 4.0,
    "师生关系": 7.0,
    "工作时间": 4.0,
    "毕业去向": 7.0
  },
  "dimensionReasons": {
    "导师能力": "自称‘做学术认真’，无实证",
    "经费情况": "‘缺钱不可能’，暗示充足",
    "学生补助": "‘都是泪’，隐含发放不足或不稳定",
    "师生关系": "称‘自家兄弟’，氛围较亲和",
    "工作时间": "‘看心情’，缺乏稳定性与边界",
    "毕业去向": "‘前途无量’，主观积极判断"
  },
  "overallRecommendation": "风格随意，经费足但管理松散，适合自主性强学生。",
  "evaluations": [
    {
      "comment": "利益相关：熊哥出马，一个顶两 导师能力：做学术我是认真的 经费发放：缺钱是不可能缺钱的 学生补助：都是泪 与学生关系：都是自家兄弟 工作时间：看心情 学生毕业去向：前途无量",
      "dimensions": {}
    }
  ]
}