{
  "id": "f295004f-0e10-403e-b361-104b5224d49e",
  "name": "未知导师",
  "school": "未知学校",
  "department": "未知院系",
  "evaluationCount": 1,
  "totalScore": 4.0,
  "dimensionScores": {
    "导师能力": 5.0,
    "经费情况": 5.0,
    "学生补助": 2.0,
    "师生关系": 5.0,
    "工作时间": 5.0,
    "毕业去向": 2.0
  },
  "dimensionReasons": {
    "导师能力": "无任何能力描述",
    "经费情况": "未提及经费",
    "学生补助": "博士1200/月，远低于合理水平",
    "师生关系": "未提及关系质量",
    "工作时间": "未提及工作安排",
    "毕业去向": "几乎无人按时毕业，隐含延毕风险"
  },
  "overallRecommendation": "补助极低、毕业困难，信息缺失严重，属高风险导师",
  "evaluations": [
    {
      "comment": "学生几乎没有按时毕业的，博士生补助1200/月",
      "dimensions": {}
    }
  ]
}