{
  "id": "f55abea9-3404-46ca-b7ba-7bf1285bc1a7",
  "name": "未知导师",
  "school": "未知学校",
  "department": "未知院系",
  "evaluationCount": 1,
  "totalScore": 5.0,
  "dimensionScores": {
    "导师能力": 5.0,
    "经费情况": 5.0,
    "学生补助": 5.0,
    "师生关系": 5.0,
    "工作时间": 5.0,
    "毕业去向": 5.0
  },
  "dimensionReasons": {
    "导师能力": "仅列姓名职称，无评价内容",
    "经费情况": "信息缺失，无法判断",
    "学生补助": "信息缺失，无法判断",
    "师生关系": "信息缺失，无法判断",
    "工作时间": "信息缺失，无法判断",
    "毕业去向": "信息缺失，无法判断"
  },
  "overallRecommendation": "信息完全缺失，无法评估，建议放弃或另行核实",
  "evaluations": [
    {
      "comment": "徐启建 博士生导师 计算机系统结构",
      "dimensions": {}
    }
  ]
}