{
  "id": "fc141fd9-e437-4cc0-8c79-a9a2a85e27a3",
  "name": "未知导师",
  "school": "未知学校",
  "department": "未知院系",
  "evaluationCount": 1,
  "totalScore": 2.5,
  "dimensionScores": {
    "导师能力": 0.0,
    "经费情况": 5.0,
    "学生补助": 5.0,
    "师生关系": 0.0,
    "工作时间": 5.0,
    "毕业去向": 0.0
  },
  "dimensionReasons": {
    "导师能力": "学生称‘什么都不懂，根本不管你’",
    "经费情况": "未提及",
    "学生补助": "未提及",
    "师生关系": "明确负面：‘特别坑，根本不管你’",
    "工作时间": "未提及",
    "毕业去向": "‘这个时候导师一定不要选’暗示极差"
  },
  "overallRecommendation": "强烈不推荐，存在严重失职风险",
  "evaluations": [
    {
      "comment": "学生毕业去向：这个时候导师一定不要选，特别坑，什么都不懂，根本不管你",
      "dimensions": {}
    }
  ]
}