{
  "id": "fe00cddb-37d3-49e9-9890-1ec430e23149",
  "name": "未知导师",
  "school": "未知学校",
  "department": "未知院系",
  "evaluationCount": 1,
  "totalScore": 4.83,
  "dimensionScores": {
    "导师能力": 5.0,
    "经费情况": 5.0,
    "学生补助": 5.0,
    "师生关系": 4.0,
    "工作时间": 5.0,
    "毕业去向": 5.0
  },
  "dimensionReasons": {
    "导师能力": "未提供有效能力信息",
    "经费情况": "未提及经费发放情况",
    "学生补助": "未提及学生补助情况",
    "师生关系": "‘报了有点后悔’，隐含负面体验",
    "工作时间": "未提及工作时间安排",
    "毕业去向": "未提及毕业去向"
  },
  "overallRecommendation": "消极反馈明确但信息不足，存在较高不确定性风险",
  "evaluations": [
    {
      "comment": "报了有点后悔吧 。",
      "dimensions": {}
    }
  ]
}